xenoslib/__init__.py
xenoslib/__main__.py
xenoslib/about.py
xenoslib/base.py
xenoslib/dev.py
xenoslib/extend.py
xenoslib/linux.py
xenoslib/mail.py
xenoslib/mock.py
xenoslib/onedrive.py
xenoslib/time_utils.py
xenoslib/win_trayicon.py
xenoslib/windows.py
xenoslib/tools/__init__.py
xenoslib/tools/config_loader.py
xenoslib-0.4.2.dist-info/licenses/LICENSE
xenoslib-0.4.2.dist-info/METADATA
xenoslib-0.4.2.dist-info/WHEEL
xenoslib-0.4.2.dist-info/top_level.txt
xenoslib-0.4.2.dist-info/RECORD
