Metadata-Version: 2.4
Name: xenoslib
Version: 0.4.2
Summary: Xenos' common lib
Home-page: https://github.com/XenosLu/xenoslib.git
Author: Xenocider
Author-email: xenos.lu@gmail.com
License: MIT License
Requires-Python: >=3.7
License-File: LICENSE
Requires-Dist: PyYAML>=5.4
Requires-Dist: IMAPClient>=2.3.1
Requires-Dist: pywin32>=225; sys_platform == "win32"
Requires-Dist: requests>=2.19; python_version >= "3.10"
Requires-Dist: requests>=2.0.0; python_version <= "3.9"
Provides-Extra: colorful
Requires-Dist: colorama>=0.4.4; sys_platform == "win32" and extra == "colorful"
Provides-Extra: mock
Requires-Dist: requests_mock>=1.9.3; extra == "mock"
Dynamic: author
Dynamic: author-email
Dynamic: description-content-type
Dynamic: home-page
Dynamic: license
Dynamic: license-file
Dynamic: provides-extra
Dynamic: requires-dist
Dynamic: requires-python
Dynamic: summary
